agentparse/__init__.py
agentparse/agent_metadata.py
agentparse/agent_parse.py
agentparse/file_processing.py
agentparse/function_to_basemodel.py
agentparse/json_output_parser.py
agentparse/main.py
agentparse/pandas_utils.py
agentparse/whitespace.py
agentparse/yaml_model.py
agentparse/yaml_output_parser.py
agentparse-0.0.3.dist-info/LICENSE
agentparse-0.0.3.dist-info/METADATA
agentparse-0.0.3.dist-info/WHEEL
agentparse-0.0.3.dist-info/RECORD
